pycode_info/__init__.py
pycode_info/ccv.py
pycode_info/colors.py
pycode_info/flake8er.py
pycode_info/lang_info.py
pycode_info/utils.py
pycode_info-0.1.16.dist-info/licenses/LICENSE
pycode_info-0.1.16.dist-info/METADATA
pycode_info-0.1.16.dist-info/WHEEL
pycode_info-0.1.16.dist-info/top_level.txt
pycode_info-0.1.16.dist-info/RECORD
