Metadata-Version: 2.4
Name: pycode-info
Version: 0.1.16
Summary: A tool to analyze Python code complexity and style.
Author-email: Justus <justus.d2025@gmail.com>
License: MIT License
Project-URL: homepage, https://github.com/justusdecker/pycode-info
Requires-Python: >=3.8
License-File: LICENSE
Requires-Dist: flake8
Requires-Dist: flake8-json
Dynamic: license-file
